{
  "type": "immersiveengineering:metal_press",
  "mold": {
    "item": "immersiveengineering:mold_plate"
  },
  "result": {
    "item": "moreplates:refined_glowstone_plate"
  },
  "conditions": [
    {
      "values": [
        {
          "type": "moreplates:isconfigenabled",
          "config_setting": "enable_plate"
        },
        {
          "item": "moreplates:refined_glowstone_plate",
          "type": "forge:item_exists"
        }
      ],
      "type": "forge:and"
    }
  ],
  "input": {
    "tag": "forge:ingots/refined_glowstone"
  },
  "energy": 2400
}