{
  "type": "forge:conditional",
  "recipes": [
    {
      "conditions": [
        {
          "values": [
            {
              "type": "moreplates:isconfigenabled",
              "config_setting": "enable_plate"
            },
            {
              "item": "moreplates:nether_quartz_plate",
              "type": "forge:item_exists"
            }
          ],
          "type": "forge:and"
        }
      ],
      "recipe": {
        "type": "minecraft:crafting_shaped",
        "pattern": [
          "H",
          "I",
          "I"
        ],
        "key": {
          "H": [],
          "I": {
            "tag": "forge:gems/quartz"
          }
        },
        "result": {
          "item": "moreplates:nether_quartz_plate"
        }
      }
    }
  ]
}